thquickjs/__init__.py
thquickjs/thquickjs.py
thquickjs-0.9.26.dist-info/LICENSE
thquickjs-0.9.26.dist-info/WHEEL
thquickjs-0.9.26.dist-info/METADATA
thquickjs-0.9.26.dist-info/RECORD
