Metadata-Version: 2.1
Name: thquickjs
Version: 0.9.26
Summary: Tangled QuickJS Javascript Engine binding library
Home-page: https://gitlab.com/tangledlabs/thquickjs
License: BSD 3-clause
Keywords: tangled,thquickjs,quickjs,tangledhub,tangledlab,tangledcloud,tangledgroup
Author: Tangled
Author-email: info@tangledgroup.com
Requires-Python: >=3.10,<4.0
Classifier: Development Status :: 4 - Beta
Classifier: Intended Audience :: Developers
Classifier: License :: OSI Approved :: BSD License
Classifier: License :: Other/Proprietary License
Classifier: Operating System :: OS Independent
Classifier: Programming Language :: Python
Classifier: Programming Language :: Python :: 3
Classifier: Programming Language :: Python :: 3.10
Classifier: Programming Language :: Python :: 3.11
Classifier: Programming Language :: Python :: 3.10
Classifier: Programming Language :: Python :: 3.11
Classifier: Topic :: Software Development :: Libraries :: Python Modules
Requires-Dist: quickjs (>=1.19.2,<2.0.0)
Requires-Dist: thresult (>=0.9.23,<0.10.0)
Project-URL: Repository, https://gitlab.com/tangledlabs/thquickjs
